hatch_project/Excel1.py
hatch_project/__about__.py
hatch_project/__init__.py
hatch_project/scraping.py
hatch_project-0.4.1.dist-info/METADATA
hatch_project-0.4.1.dist-info/WHEEL
hatch_project-0.4.1.dist-info/licenses/LICENSE.txt
hatch_project-0.4.1.dist-info/RECORD
