Metadata-Version: 2.3
Name: hatch-project
Version: 0.4.1
Project-URL: Documentation, https://github.com/U.N. Owen/hatch-project#readme
Project-URL: Issues, https://github.com/U.N. Owen/hatch-project/issues
Project-URL: Source, https://github.com/U.N. Owen/hatch-project
Author-email: "U.N. Owen" <void@some.where>
License-Expression: MIT
License-File: LICENSE.txt
Classifier: Development Status :: 4 - Beta
Classifier: Programming Language :: Python
Classifier: Programming Language :: Python :: 3.8
Classifier: Programming Language :: Python :: 3.9
Classifier: Programming Language :: Python :: 3.10
Classifier: Programming Language :: Python :: 3.11
Classifier: Programming Language :: Python :: 3.12
Classifier: Programming Language :: Python :: Implementation :: CPython
Classifier: Programming Language :: Python :: Implementation :: PyPy
Requires-Python: >=3.8
Requires-Dist: bs4==0.0.1
Requires-Dist: requests>=2.28.8
